{
  "b": 0,
  "disableInputWhenNotFocused": true,
  "mangledName": "game_32over",
  "name": "game over",
  "oglFOV": 90,
  "oglZFar": 500,
  "oglZNear": 1,
  "r": 0,
  "standardSortMethod": true,
  "stopSoundsOnStartup": true,
  "title": "",
  "v": 0,
  "uiSettings": {
    "grid": false,
    "gridType": "rectangular",
    "gridWidth": 32,
    "gridHeight": 32,
    "gridOffsetX": 0,
    "gridOffsetY": 0,
    "gridColor": 10401023,
    "snap": false,
    "zoomFactor": 0.5,
    "windowMask": false
  },
  "objectsGroups": [],
  "variables": [],
  "instances": [
    {
      "angle": 0,
      "customSize": false,
      "height": 0,
      "layer": "",
      "locked": false,
      "name": "gameover",
      "persistentUuid": "33314ed3-13e4-4262-b8ad-9b68380a22aa",
      "width": 0,
      "x": 845,
      "y": 282,
      "zOrder": 1,
      "numberProperties": [],
      "stringProperties": [],
      "initialVariables": []
    },
    {
      "angle": 0,
      "customSize": false,
      "height": 0,
      "layer": "",
      "locked": false,
      "name": "Highscore",
      "persistentUuid": "3e761d3d-9c5c-4861-818b-bdcf50069213",
      "width": 0,
      "x": 588,
      "y": 429,
      "zOrder": 2,
      "numberProperties": [],
      "stringProperties": [],
      "initialVariables": []
    },
    {
      "angle": 0,
      "customSize": false,
      "height": 0,
      "layer": "",
      "locked": false,
      "name": "hsn",
      "persistentUuid": "eea216be-29cd-4acd-95a1-b11552082e34",
      "width": 0,
      "x": 940,
      "y": 435,
      "zOrder": 4,
      "numberProperties": [],
      "stringProperties": [],
      "initialVariables": []
    },
    {
      "angle": 0,
      "customSize": false,
      "height": 0,
      "layer": "",
      "locked": false,
      "name": "Score",
      "persistentUuid": "25219f6a-7d1a-4ee7-9131-b212c4abdbe8",
      "width": 0,
      "x": 482,
      "y": 531,
      "zOrder": 5,
      "numberProperties": [],
      "stringProperties": [],
      "initialVariables": []
    },
    {
      "angle": 0,
      "customSize": false,
      "height": 0,
      "layer": "",
      "locked": false,
      "name": "Snumber",
      "persistentUuid": "1560ad3c-33c7-4b23-8d06-5696fb4e364e",
      "width": 0,
      "x": 702,
      "y": 539,
      "zOrder": 6,
      "numberProperties": [],
      "stringProperties": [],
      "initialVariables": []
    }
  ],
  "objects": [
    {
      "bold": false,
      "italic": false,
      "name": "gameover",
      "smoothed": true,
      "tags": "",
      "type": "TextObject::Text",
      "underlined": false,
      "variables": [],
      "effects": [],
      "behaviors": [],
      "string": "Game Over",
      "font": "MechanismoRegular-p7ywa.otf",
      "characterSize": 60,
      "color": {
        "b": 255,
        "g": 255,
        "r": 255
      }
    }
  ],
  "events": [
    {
      "disabled": false,
      "folded": false,
      "type": "BuiltinCommonInstructions::Standard",
      "conditions": [
        {
          "type": {
            "inverted": false,
            "value": "DepartScene"
          },
          "parameters": [
            ""
          ],
          "subInstructions": []
        }
      ],
      "actions": [
        {
          "type": {
            "inverted": false,
            "value": "EcrireFichierExp"
          },
          "parameters": [
            "\"HighScore\"",
            "\"\"",
            "GlobalVariable(Highscore)"
          ],
          "subInstructions": []
        }
      ],
      "events": []
    },
    {
      "disabled": false,
      "folded": false,
      "type": "BuiltinCommonInstructions::Link",
      "include": {
        "includeConfig": 0
      },
      "target": "Highscore"
    }
  ],
  "layers": [
    {
      "ambientLightColorB": 0,
      "ambientLightColorG": 0,
      "ambientLightColorR": 1,
      "followBaseLayerCamera": false,
      "isLightingLayer": false,
      "name": "",
      "visibility": true,
      "cameras": [
        {
          "defaultSize": true,
          "defaultViewport": true,
          "height": 0,
          "viewportBottom": 1,
          "viewportLeft": 0,
          "viewportRight": 1,
          "viewportTop": 0,
          "width": 0
        }
      ],
      "effects": []
    }
  ],
  "behaviorsSharedData": []
}